<!-- Only constraint is optional-->
<!-- Miner can be single or cluster-->
<input>
    <miner>single</miner>
    <filename>examples/106_N_train.txt</filename>
    <prds>
        <prd>p0:0::</prd>
        <prd>p1:0::</prd>
        <prd>p2:0::</prd>
        <prd>p3:0::</prd>
        <prd>p4:0::</prd>
        <prd>p5:0::</prd>
    </prds>
    <bltls>
	    <bltl>(G[25](p0)&F[48](p1&F[30](p2&F[11](p3&F[30](G[8](p4)&F[57](p5))))))</bltl>
    </bltls>
    <init>p0.left:0.0000, p0.right:0.2574, p1.left:0.1198, p1.right:0.3902, p2.left:0.0000, p2.right:0.2252, p3.left:0.8, p3.right:1.0000, p4.left:0.0000, p4.right:0.1847, p5.left:0.0948, p5.right:0.5050</init>
    <constraints>
    <constraint>p1>p2</constraint>
    <constraint>p3>p2</constraint>
    <constraint>p3>p4</constraint>
    <constraint>p5>p4</constraint>
    </constraints>
    <weights>
        <weight>k1:0.2</weight>
        <weight>k2:0.2</weight>
        <weight>k3:0.2</weight>
        <weight>p3:0.1</weight>
        <weight>p2:0.1</weight>
        <weight>p4:0.1</weight>
        <weight>p1:0.1</weight>
    </weights>
    <config>
        <N_TRIES>1000</N_TRIES>
        <ITERS_FIXED_T>200</ITERS_FIXED_T>
        <STEP_SIZE>0.2</STEP_SIZE>
        <K>1.0</K>
        <T_INITIAL>0.008</T_INITIAL>
        <MU_T>1.001</MU_T>
        <T_MIN>0.001</T_MIN>
    </config>
</input>

